{
  "mcpServers": {
    "mcp-tools-py": {
      "type": "stdio",
      "command": "${MCP_CODER_VENV_PATH}/mcp-tools-py",
      "args": [
        "--project-dir",
        "${MCP_CODER_PROJECT_DIR}",
        "--python-executable",
        "${VIRTUAL_ENV}/bin/python",
        "--venv-path",
        "${VIRTUAL_ENV}",
        "--test-folder",
        "tests",
        "--log-level",
        "INFO"
      ],
      "env": {
        "PYTHONPATH": "${MCP_CODER_PROJECT_DIR}/src"
      }
    },
    "mcp-workspace": {
      "type": "stdio",
      "command": "${MCP_CODER_VENV_PATH}/mcp-workspace",
      "args": [
        "--project-dir",
        "${MCP_CODER_PROJECT_DIR}",
        "--log-level",
        "INFO",
        "--reference-project",
        "name=mcp-workspace,path=${HOME}/Documents/GitHub/mcp-workspace,url=https://github.com/MarcusJellinghaus/mcp-workspace",
        "--reference-project",
        "name=mcp-config,path=${HOME}/Documents/GitHub/mcp-config,url=https://github.com/MarcusJellinghaus/mcp-config",
        "--reference-project",
        "name=mcp-coder-utils,path=${HOME}/Documents/GitHub/mcp-coder-utils,url=https://github.com/MarcusJellinghaus/mcp-coder-utils",
        "--reference-project",
        "name=mcp-tools-py,path=${HOME}/Documents/GitHub/mcp-tools-py,url=https://github.com/MarcusJellinghaus/mcp-tools-py",
        "--reference-project",
        "name=mcp-tools-sql,path=${HOME}/Documents/GitHub/mcp-tools-sql,url=https://github.com/MarcusJellinghaus/mcp-tools-sql"
      ],
      "env": {
        "PYTHONPATH": "${MCP_CODER_VENV_DIR}/lib"
      }
    }
  }
}
